pypepper/__init__.py
pypepper/errors.py
pypepper/exceptions.py
pypepper/loader.py
pypepper/logo.py
pypepper/common/__init__.py
pypepper/common/cache.py
pypepper/common/config.py
pypepper/common/log.py
pypepper/common/options.py
pypepper/common/system.py
pypepper/common/version.py
pypepper/common/context/__init__.py
pypepper/common/context/context.py
pypepper/common/context/interfaces.py
pypepper/common/security/__init__.py
pypepper/common/security/crypto/__init__.py
pypepper/common/security/crypto/digest.py
pypepper/common/security/crypto/salt.py
pypepper/common/security/crypto/elliptic/__init__.py
pypepper/common/security/crypto/elliptic/algorithm.py
pypepper/common/security/crypto/elliptic/ecdsa.py
pypepper/common/security/crypto/elliptic/interfaces.py
pypepper/common/utils/__init__.py
pypepper/common/utils/random.py
pypepper/common/utils/retry.py
pypepper/common/utils/time.py
pypepper/common/utils/uuid.py
pypepper/event/__init__.py
pypepper/event/event.py
pypepper/event/interfaces.py
pypepper/fsm/__init__.py
pypepper/fsm/fsm.py
pypepper/fsm/interfaces.py
pypepper/helper/__init__.py
pypepper/helper/db/__init__.py
pypepper/helper/db/interfaces.py
pypepper/helper/db/mongodb.py
pypepper/helper/db/mysql.py
pypepper/network/__init__.py
pypepper/network/http/__init__.py
pypepper/network/http/interfaces.py
pypepper/network/http/response.py
pypepper/network/http/server.py
pypepper/network/http/handlers/__init__.py
pypepper/network/http/handlers/base.py
pypepper/network/http/handlers/handlers.py
pypepper/scheduler/__init__.py
pypepper/scheduler/base.py
pypepper/scheduler/channel.py
pypepper/scheduler/events.py
pypepper/scheduler/executor.py
pypepper/scheduler/job.py
pypepper/scheduler/status.py
pypepper/scheduler/tag.py
pypepper/scheduler/task.py
pypepper/scheduler/workflow.py
pypepper-0.4.1.dist-info/METADATA
pypepper-0.4.1.dist-info/WHEEL
pypepper-0.4.1.dist-info/licenses/LICENSE
pypepper-0.4.1.dist-info/RECORD
