Metadata-Version: 2.4
Name: pypepper
Version: 0.4.1
Summary: PyPepper is a microservice toolkit written in Python.
Project-URL: Homepage, https://github.com/jovijovi/pypepper
Project-URL: Repository, https://github.com/jovijovi/pypepper
Project-URL: Issues, https://github.com/jovijovi/pypepper/issues
Author-email: jovijovi <mageyul@hotmail.com>
License-File: LICENSE
Classifier: License :: OSI Approved :: MIT License
Classifier: Operating System :: OS Independent
Classifier: Programming Language :: Python :: 3
Requires-Python: >=3.10
Requires-Dist: arrow==1.4.0
Requires-Dist: cachetools==6.2.4
Requires-Dist: cryptography==46.0.3
Requires-Dist: fastapi==0.128.0
Requires-Dist: loguru==0.7.3
Requires-Dist: mongoengine==0.29.1
Requires-Dist: pip==25.3
Requires-Dist: pymysql==1.1.2
Requires-Dist: python-box==7.3.2
Requires-Dist: pyyaml==6.0.3
Requires-Dist: sqlalchemy==2.0.45
Requires-Dist: uvicorn==0.40.0
